neogram/__init__.py
neogram/fgram.py
neogram/ii.py
neogram-9.3.dist-info/licenses/LICENSE
neogram-9.3.dist-info/METADATA
neogram-9.3.dist-info/WHEEL
neogram-9.3.dist-info/top_level.txt
neogram-9.3.dist-info/RECORD
