Metadata-Version: 2.4
Name: neogram
Version: 9.3
Summary: neogram is a lightweight Python module for working with the Telegram Bot API and AI. It combines simple Telegram workflows with powerful features like text and image generation, translation, and more.
Author: SiriLV
Author-email: siriteamrs@gmail.com
License: MIT
Classifier: Programming Language :: Python :: 3
Classifier: Programming Language :: Python :: 3.10
Classifier: License :: OSI Approved :: MIT License
Classifier: Operating System :: OS Independent
Requires-Python: >=3.10
License-File: LICENSE
Requires-Dist: requests>=2.32.5
Requires-Dist: bs4>=0.0.2
Dynamic: author
Dynamic: author-email
Dynamic: classifier
Dynamic: description
Dynamic: description-content-type
Dynamic: license
Dynamic: license-file
Dynamic: requires-dist
Dynamic: requires-python
Dynamic: summary
